opentsdb_python_metrics/__init__.py
opentsdb_python_metrics/metric_wrappers.py
opentsdb_python_metrics-0.2.0.dist-info/METADATA
opentsdb_python_metrics-0.2.0.dist-info/WHEEL
opentsdb_python_metrics-0.2.0.dist-info/top_level.txt
opentsdb_python_metrics-0.2.0.dist-info/RECORD
