Metadata-Version: 2.1
Name: opentsdb-python-metrics
Version: 0.2.0
Summary: Library for collecting and storing metrics from python methods
Home-page: UNKNOWN
Author: Jon Nation
Author-email: jnation@lco.global
License: GNU GPL
Platform: UNKNOWN
Requires-Dist: opentsdb-http-client (>=0.2.0)
